setup.py
SeisCM.egg-info/PKG-INFO
SeisCM.egg-info/SOURCES.txt
SeisCM.egg-info/dependency_links.txt
SeisCM.egg-info/top_level.txt
seiscm/__init__.py
seiscm/seiscm.py
tests/__init__.py
tests/test_seiscm.py